c_api_extract.py
c_api_extract-0.7.0.dist-info/METADATA
c_api_extract-0.7.0.dist-info/WHEEL
c_api_extract-0.7.0.dist-info/entry_points.txt
c_api_extract-0.7.0.dist-info/top_level.txt
c_api_extract-0.7.0.dist-info/RECORD
