Metadata-Version: 2.1
Name: c-api-extract
Version: 0.7.0
Summary: Automatic extraction of C APIs from header files using libclang
Home-page: https://github.com/gilzoide/c_api_extract-py
Author: gilzoide
Author-email: gilzoide@gmail.com
License: Unlicense
Project-URL: Source, https://github.com/gilzoide/c_api_extract-py
Project-URL: Tracker, https://github.com/gilzoide/c_api_extract-py/issues
Keywords: c header clang
Platform: UNKNOWN
Classifier: Development Status :: 3 - Alpha
Classifier: Intended Audience :: Developers
Classifier: License :: Public Domain
Classifier: Programming Language :: Python :: 3
Classifier: Topic :: Software Development :: Compilers
Requires-Dist: clang
Requires-Dist: docopt
